CUP_EXAM/__init__.py
CUP_EXAM/backend.py
CUP_EXAM/frontend.py
CUP_EXAM-2.6.8.dist-info/LICENSE
CUP_EXAM-2.6.8.dist-info/METADATA
CUP_EXAM-2.6.8.dist-info/WHEEL
CUP_EXAM-2.6.8.dist-info/entry_points.txt
CUP_EXAM-2.6.8.dist-info/top_level.txt
CUP_EXAM-2.6.8.dist-info/zip-safe
CUP_EXAM-2.6.8.dist-info/RECORD
