Metadata-Version: 2.1
Name: CUP-EXAM
Version: 2.6.8
Summary: Check exam information of China university of petroleum (Beijing)
Home-page: https://github.com/Rhythmicc/CUP_EXAM
Author: RhythmLian
License: MIT
Keywords: Check exam information
Platform: UNKNOWN
Classifier: Programming Language :: Python :: 3
Classifier: License :: OSI Approved :: MIT License
Classifier: Operating System :: OS Independent
Requires-Dist: xlrd
Requires-Dist: requests
Requires-Dist: jieba
